pushover_jb/__init__.py
pushover_jb/message.py
pushover_jb-1.0.4.dist-info/LICENSE
pushover_jb-1.0.4.dist-info/METADATA
pushover_jb-1.0.4.dist-info/WHEEL
pushover_jb-1.0.4.dist-info/top_level.txt
pushover_jb-1.0.4.dist-info/RECORD
