Metadata-Version: 2.1
Name: pushover-jb
Version: 1.0.4
Summary: A simple Pushover messages API wrapper.
Author-email: Jerry de Boer <info@hybridsoftworks.com>
Project-URL: Homepage, https://github.com/JerrydeB/pushover
Project-URL: Issues, https://github.com/JerrydeB/pushover/issues
Classifier: Programming Language :: Python :: 3
Classifier: License :: OSI Approved :: MIT License
Classifier: Operating System :: OS Independent
License-File: LICENSE
